htmlcompare/__init__.py
htmlcompare/cli.py
htmlcompare/compare.py
htmlcompare/compare_css.py
htmlcompare/elements.py
htmlcompare/nodes.py
htmlcompare/normalize.py
htmlcompare/options.py
htmlcompare/parser.py
htmlcompare/result.py
htmlcompare/testutils.py
htmlcompare/tests/__init__.py
htmlcompare/tests/compare_test.py
htmlcompare/tests/doctype_detection_test.py
htmlcompare/tests/parser_test.py
htmlcompare-0.4.1.dist-info/licenses/LICENSE.txt
htmlcompare-0.4.1.dist-info/METADATA
htmlcompare-0.4.1.dist-info/WHEEL
htmlcompare-0.4.1.dist-info/entry_points.txt
htmlcompare-0.4.1.dist-info/top_level.txt
htmlcompare-0.4.1.dist-info/zip-safe
htmlcompare-0.4.1.dist-info/RECORD
