Metadata-Version: 2.4
Name: HTMLCompare
Version: 0.4.1
Summary: library to compare HTML while ignoring non-functional differences
Home-page: https://github.com/FelixSchwarz/htmlcompare
Author: Felix Schwarz
Author-email: felix.schwarz@oss.schwarz.eu
License: MIT
Project-URL: Code, https://github.com/FelixSchwarz/htmlcompare
Project-URL: Issue tracker, https://github.com/FelixSchwarz/htmlcompare/issues
Classifier: Development Status :: 4 - Beta
Classifier: Intended Audience :: Developers
Classifier: License :: OSI Approved :: MIT License
Classifier: Programming Language :: Python :: 3
Classifier: Programming Language :: Python :: 3.9
Classifier: Programming Language :: Python :: 3.10
Classifier: Programming Language :: Python :: 3.11
Classifier: Programming Language :: Python :: 3.12
Classifier: Programming Language :: Python :: 3.13
Classifier: Programming Language :: Python :: 3.14
Classifier: Topic :: Internet :: WWW/HTTP
Classifier: Topic :: Text Processing :: Markup :: HTML
Requires-Python: >=3.9
License-File: LICENSE.txt
Requires-Dist: html5lib
Requires-Dist: tinycss2
Provides-Extra: testing
Requires-Dist: pytest; extra == "testing"
Dynamic: license-file
